osm_guesstimator/__init__.py
osm_guesstimator/osm_guesstimator.py
osm_guesstimator-0.1.dist-info/METADATA
osm_guesstimator-0.1.dist-info/WHEEL
osm_guesstimator-0.1.dist-info/RECORD
