Metadata-Version: 2.4
Name: osm_guesstimator
Version: 0.1
Summary: Guesstimate properties like street width in incomplete osm data
Project-URL: Homepage, https://github.com/PizzaTreeIsland/osm_guesstimator
Project-URL: Issues, https://github.com/PizzaTreeIsland/osm_guesstimator/issues
Author-email: PizzaTreeIsland <pizzatreeisland@protonmail.com>
License-Expression: MIT
Keywords: estimate,geojson,height,incomplete data,openstreetmap,osm,width
Classifier: Operating System :: OS Independent
Classifier: Programming Language :: Python :: 3
Requires-Python: >=3.6
